LICENSE
setup.py
annogen/__init__.py
annogen/__main__.py
annogen.egg-info/PKG-INFO
annogen.egg-info/SOURCES.txt
annogen.egg-info/dependency_links.txt
annogen.egg-info/entry_points.txt
annogen.egg-info/top_level.txt