Metadata-Version: 2.1
Name: annogen
Version: 3.408
Summary: Annotator Generator, an examples-driven generator of fast text annotators for language learning aids etc
Home-page: http://ssb22.user.srcf.net/adjuster/annogen.html
Author: Silas S. Brown
Author-email: ssb22@cam.ac.uk
License: Apache 2
Platform: any
Classifier: Programming Language :: Python :: 2
Classifier: Programming Language :: Python :: 3
Classifier: License :: OSI Approved :: Apache Software License
Classifier: Operating System :: OS Independent
Requires-Python: >=2.7
License-File: LICENSE
